streamlit_ai_voice_chat/__init__.py
streamlit_ai_voice_chat/options_builder.py
streamlit_ai_voice_chat/test_app.py
streamlit_ai_voice_chat/frontend/build/animation_1.mp4
streamlit_ai_voice_chat/frontend/build/animation_2.mp4
streamlit_ai_voice_chat/frontend/build/asset-manifest.json
streamlit_ai_voice_chat/frontend/build/bootstrap.min.css
streamlit_ai_voice_chat/frontend/build/bootstrap.min.css.map
streamlit_ai_voice_chat/frontend/build/hoots.png
streamlit_ai_voice_chat/frontend/build/hootsAndHootie.png
streamlit_ai_voice_chat/frontend/build/index.html
streamlit_ai_voice_chat/frontend/build/precache-manifest.06c4409b5605bc7d242f74767fb072d1.js
streamlit_ai_voice_chat/frontend/build/service-worker.js
streamlit_ai_voice_chat/frontend/build/test_audio.mp3
streamlit_ai_voice_chat/frontend/build/models/age_gender_model-shard1
streamlit_ai_voice_chat/frontend/build/models/age_gender_model-weights_manifest.json
streamlit_ai_voice_chat/frontend/build/models/face_expression_model-shard1
streamlit_ai_voice_chat/frontend/build/models/face_expression_model-weights_manifest.json
streamlit_ai_voice_chat/frontend/build/models/face_landmark_68_model-shard1
streamlit_ai_voice_chat/frontend/build/models/face_landmark_68_model-weights_manifest.json
streamlit_ai_voice_chat/frontend/build/models/face_landmark_68_tiny_model-shard1
streamlit_ai_voice_chat/frontend/build/models/face_landmark_68_tiny_model-weights_manifest.json
streamlit_ai_voice_chat/frontend/build/models/face_recognition_model-shard1
streamlit_ai_voice_chat/frontend/build/models/face_recognition_model-shard2
streamlit_ai_voice_chat/frontend/build/models/face_recognition_model-weights_manifest.json
streamlit_ai_voice_chat/frontend/build/models/mtcnn_model-shard1
streamlit_ai_voice_chat/frontend/build/models/mtcnn_model-weights_manifest.json
streamlit_ai_voice_chat/frontend/build/models/ssd_mobilenetv1_model-shard1
streamlit_ai_voice_chat/frontend/build/models/ssd_mobilenetv1_model-shard2
streamlit_ai_voice_chat-0.1.9.dist-info/licenses/LICENSE
streamlit_ai_voice_chat-0.1.9.dist-info/METADATA
streamlit_ai_voice_chat-0.1.9.dist-info/WHEEL
streamlit_ai_voice_chat-0.1.9.dist-info/top_level.txt
streamlit_ai_voice_chat-0.1.9.dist-info/RECORD
