Metadata-Version: 2.4
Name: streamlit-ai-voice-chat
Version: 0.1.9
Summary: A Streamlit custom component that provides a chat window with voice capabilities for conversation handling
Home-page: https://github.com/nafets33/ai_voice_chat
Author: Stefan Stapinski
Author-email: stefanstapinski@gmail.com
Project-URL: Bug Tracker, https://github.com/nafets33/ai_voice_chat/issues
Classifier: Development Status :: 3 - Alpha
Classifier: Intended Audience :: Developers
Classifier: License :: OSI Approved :: MIT License
Classifier: Programming Language :: Python :: 3
Classifier: Programming Language :: Python :: 3.7
Classifier: Programming Language :: Python :: 3.8
Classifier: Programming Language :: Python :: 3.9
Classifier: Programming Language :: Python :: 3.10
Classifier: Programming Language :: Python :: 3.11
Classifier: Operating System :: OS Independent
Requires-Python: >=3.7
License-File: LICENSE
Requires-Dist: streamlit>=1.0.0
Dynamic: author
Dynamic: author-email
Dynamic: classifier
Dynamic: description
Dynamic: description-content-type
Dynamic: home-page
Dynamic: license-file
Dynamic: project-url
Dynamic: requires-dist
Dynamic: requires-python
Dynamic: summary
